rfcdl/.gitignore
rfcdl/__init__.py
rfcdl/__main__.py
rfcdl/arguments.py
rfcdl/config.py
rfcdl/document.py
rfcdl/downloader.py
rfcdl/exception.py
rfcdl/logging.py
rfcdl/rfcdl.py
rfcdl/util.py
rfcdl-1.2.9.dist-info/entry_points.txt
rfcdl-1.2.9.dist-info/LICENSE
rfcdl-1.2.9.dist-info/WHEEL
rfcdl-1.2.9.dist-info/METADATA
rfcdl-1.2.9.dist-info/RECORD
