Metadata-Version: 2.1
Name: rfcdl
Version: 1.2.9
Summary: A tool for downloading RFCs in high-speed.
License: MIT
Keywords: rfc,downloader,cli
Author: eikendev
Author-email: raphael@eiken.dev
Requires-Python: >=3.9,<4.0
Classifier: Development Status :: 4 - Beta
Classifier: Environment :: Console
Classifier: Intended Audience :: Developers
Classifier: License :: OSI Approved :: MIT License
Classifier: Operating System :: POSIX
Classifier: Programming Language :: Python :: 3
Classifier: Programming Language :: Python :: 3.10
Classifier: Programming Language :: Python :: 3.9
Classifier: Topic :: Utilities
Requires-Dist: aiofiles (>=0.7,<0.8)
Requires-Dist: aiohttp (>=3,<4)
Requires-Dist: requests (>=2,<3)
Project-URL: homepage, https://pypi.python.org/pypi/rfcdl
